{
    "name": "[BORef] FC Knights",
    "author": "Cicero",
    "source": "https://buildorderreference.com/28+2-fc-knights.html",
    "build_order": [{
            "villager_count": 6,
            "age": 1,
            "resources": {
                "wood": 0,
                "food": {
					"Sheep": 6
				},
                "gold": 0,
                "stone": 0
            },
            "notes": [
                "Build 2 @other/House_aoe2DE.png@.",
                "Send the first 6 @resource/MaleVillDE.jpg@ to @animal/Sheep_aoe2DE.png@."
            ]
        },
        {
            "villager_count": 10,
            "age": 1,
            "resources": {
                "wood": 4,
                "food": {
					"Sheep": 6
				},
                "gold": 0,
                "stone": 0
            },
            "notes": [
                "Send the next 4 @resource/MaleVillDE.jpg@ to @resource/Aoe2de_wood.png@ on 1 @lumber_camp/Lumber_camp_aoe2de.png@"
            ]
        },
        {
            "villager_count": 11,
            "age": 1,
            "resources": {
                "wood": 4,
                "food": {
					"Boar": 7
				},
                "gold": 0,
                "stone": 0
            },
            "notes": [
                "Next @resource/MaleVillDE.jpg@ lures @animal/Boar_aoe2DE.png@"
            ]
        },
        {
            "villager_count": 16,
            "age": 1,
            "resources": {
                "wood": 4,
                "food": {
					"Boar": 7,
					"Berries":5
				},
                "gold": 0,
                "stone": 0
            },
            "notes": [
				"Build 2 @other/House_aoe2DE.png@ + @mill/Mill_aoe2de.png@",
				"5 next @resource/MaleVillDE.jpg@ to @resource/BerryBushDE.png@"
            ]
        },
        {
            "villager_count": 18,
            "age": 1,
            "resources": {
                "wood": 4,
                "food": {
					"Boar": 7,
					"Berries": 5,
					"Farms": 2
				},
                "gold": 0,
                "stone": 0
            },
            "notes": [
                "Send 2 more @resource/MaleVillDE.jpg@ on @animal/Boar_aoe2DE.png@",
				"Transfer 2 to @mill/FarmDE.png@",
				"Lure the second @animal/Boar_aoe2DE.png@"
            ]
        },
        {
            "villager_count": 24,
            "age": 1,
            "resources": {
                "wood": 10,
                "food": {
					"Boar": 7,
					"Berries": 5,
					"Farms": 2
				},
                "gold": 0,
                "stone": 0
            },
            "notes": [
				"Build a @other/House_aoe2DE.png@",
                "Go to 10 @resource/MaleVillDE.jpg@ to @resource/Aoe2de_wood.png@ on 2 @lumber_camp/Lumber_camp_aoe2de.png@"
            ]
        },
        {
            "villager_count": 27,
            "age": 1,
            "resources": {
                "wood": 10,
                "food": {
					"Boar": 7,
					"Berries": 5,
					"Farms": 2
				},
                "gold": 3,
                "stone": 0
            },
            "notes": [
                "Send 3 @resource/MaleVillDE.jpg@ to @resource/Aoe2de_gold.png@"
            ]
        },
        {
            "villager_count": 27,
            "age": 1,
            "resources": {
                "wood": 10,
                "food": {
					"Berries": 5,
					"Farms": 8
				},
                "gold": 3,
                "stone": 0
            },
            "notes": [
                "Click @town_center/LoomDE.png@ and @age/FeudalAgeIconDE.png@",
				"Gradually transfer 8 @resource/MaleVillDE.jpg@ to @mill/FarmDE.png@",
				"Use 1 @resource/Aoe2de_food.png@ vill to build a @barracks/Barracks_aoe2DE.png@"
            ]
        },
        {
            "villager_count": 29,
            "age": 2,
            "resources": {
                "wood": 10,
                "food": {
					"Berries": 5,
					"Farms": 8
				},
                "gold": 5,
                "stone": 0
            },
            "notes": [
                "Build a @stable/Stable_aoe2DE.png@ and a @blacksmith/Blacksmith_aoe2de.png@",
                "Send 2 new @resource/MaleVillDE.jpg@ to @resource/Aoe2de_gold.png@"
            ]
        },
		        {
            "villager_count": 29,
            "age": 2,
            "resources": {
                "wood": 10,
                "food": {
					"Berries": 4,
					"Farms": 10
				},
                "gold": 5,
                "stone": 0
            },
            "notes": [
				"Click @age/CastleAgeIconDE.png@",
				"@lumber_camp/DoubleBitAxe_aoe2DE.png@ + @mill/HorseCollarDE.png@",
				"+2 on @mill/FarmDE.png@ (should make 10)",
				"Build 2nd @stable/Stable_aoe2DE.png@"
            ]
        },
        {
            "villager_count": -1,
            "age": 3,
            "resources": {
                "wood": -1,
                "food": -1,
                "gold": -1,
                "stone": -1
            },
            "notes": [
				"Spam @stable/Knight_aoe2DE.png@ from 2 @stable/Stable_aoe2DE.png@",
                "Research @stable/BloodlinesDE.png@ and @blacksmith/ScaleBardingArmorDE.png@",
				"Keep making @resource/MaleVillDE.jpg@ and send them to @mill/FarmDE.png@ or @resource/Aoe2de_gold.png@",
				"Start adding @town_center/Towncenter_aoe2DE.png@ after making 10-12 @stable/Knight_aoe2DE.png@ or when no damage possible"
            ]
        }
    ]
}