{
    "name": "Juliete franks Paladins <3",
    "author": "MagnumDonger",
    "build_order": [{
            "villager_count": 6,
            "age": 1,
            "resources": {
                "wood": 0,
                "food": {
					"Sheep": 6
				},
                "gold": 0,
                "stone": 0
            },
            "notes": [
                "Build 2 @other/House_aoe2DE.png@.",
                "Send the fitst 6 @resource/MaleVillDE.jpg@ to @animal/Sheep_aoe2DE.png@."
            ]
        },
        {
            "villager_count": 10,
            "age": 1,
            "resources": {
                "wood": 4,
                "food": {
					"Sheep": 6
				},
                "gold": 0,
                "stone": 0
            },
            "notes": [
                "Send the next 4 @resource/MaleVillDE.jpg@ to @resource/Aoe2de_wood.png@ on 1 @lumber_camp/Lumber_camp_aoe2de.png@"
            ]
        },
        {
            "villager_count": 11,
            "age": 1,
            "resources": {
                "wood": 4,
                "food": {
					"Boar": 7
				},
                "gold": 0,
                "stone": 0
            },
            "notes": [
                "Next @resource/MaleVillDE.jpg@ lures @animal/Boar_aoe2DE.png@"
            ]
        },
        {
            "villager_count": 16,
            "age": 1,
            "resources": {
                "wood": 4,
                "food": {
					"Boar": 7,
					"Berries":5
				},
                "gold": 0,
                "stone": 0
            },
            "notes": [
                "5 next @resource/MaleVillDE.jpg@ to @resource/BerryBushDE.png@.",
				"Build 2 @other/House_aoe2DE.png@ + @mill/Mill_aoe2de.png@",
				"Lure the second @animal/Boar_aoe2DE.png@"
            ]
        },
        {
            "villager_count": 18,
            "age": 1,
            "resources": {
                "wood": 4,
                "food": {
					"Boar": 7,
					"Berries": 5,
					"Farms": 2
				},
                "gold": 0,
                "stone": 0
            },
            "notes": [
                "Send 2 more @resource/MaleVillDE.jpg@ on @animal/Boar_aoe2DE.png@",
				"Gradually transfer 2 weak vills to @mill/FarmDE.png@"
            ]
        },
        {
            "villager_count": 23,
            "age": 1,
            "resources": {
                "wood": 9,
                "food": {
					"Boar": 7,
					"Berries": 5,
					"Farms": 2
				},
                "gold": 0,
                "stone": 0
            },
            "notes": [
                "Go to 9 @resource/MaleVillDE.jpg@ to @resource/Aoe2de_wood.png@ on 2 @lumber_camp/Lumber_camp_aoe2de.png@",
                "Build a @other/House_aoe2DE.png@"
            ]
        },
        {
            "villager_count": 26,
            "age": 1,
            "resources": {
                "wood": 9,
                "food": {
					"Sheep": 7,
					"Berries": 5,
					"Farms": 2
				},
                "gold": 3,
                "stone": 0
            },
            "notes": [
                "Send 3 @resource/MaleVillDE.jpg@ to @resource/Aoe2de_gold.png@"
            ]
        },
        {
            "villager_count": 26,
            "age": 1,
            "resources": {
                "wood": 9,
                "food": {
					"Berries": 5,
					"Farms": 8,
					"Sheep":1
				},
                "gold": 3,
                "stone": 0
            },
            "notes": [
                "Click @town_center/LoomDE.png@ and @age/FeudalAgeIconDE.png@",
				"Gradually transfer 8 @resource/MaleVillDE.jpg@ to @mill/FarmDE.png@"
            ],
			"time":"11:15"
        },
        {
            "villager_count": 28,
            "age": 2,
            "resources": {
                "wood": 11,
                "food": {
					"Berries": 5,
					"Farms": 8,
					"Sheep":1
				},
                "gold": 3,
                "stone": 0
            },
            "notes": [
                "Build a @market/Market_aoe2DE.png@ with 2 @resource/MaleVillDE.jpg@ and a @blacksmith/Blacksmith_aoe2de.png@ with 1",
                "Send 2 new @resource/MaleVillDE.jpg@ to @resource/Aoe2de_wood.png@"
            ]
        },
		        {
            "villager_count": 28,
            "age": 2,
            "resources": {
                "wood": 14,
                "food": {
					"Berries": 3,
					"Farms": 8
				},
                "gold": 3,
                "stone": 0
            },
            "notes": [
				"Click @age/CastleAgeIconDE.png@",
				"@lumber_camp/DoubleBitAxe_aoe2DE.png@ + @mill/HorseCollarDE.png@",
				"Transfer from food until you have 14 @resource/MaleVillDE.jpg@ on @resource/Aoe2de_wood.png@"
            ],
			"time":"14:30"
        },
        {
            "villager_count": 35,
            "age": 3,
            "resources": {
                "wood": 14,
                "food": 18,
                "gold": 3,
                "stone": 0
            },
            "notes": [
				"Build 2 new @town_center/Towncenter_aoe2DE.png@, keep @resource/MaleVillDE.jpg@ production",
                "Have 1 @resource/MaleVillDE.jpg@ build houses constantly",
				"Research @lumber_camp/BowSawDE.png@"
            ]
        },
		{
            "villager_count": 41,
            "age": 3,
            "resources": {
                "wood": 14,
                "food": 18,
                "gold": 3,
                "stone": 6
            },
            "notes": [
				"6 on @resource/Aoe2de_stone.png@",
				"Go up to 22 @mill/FarmDE.png@, then @town_center/WheelbarrowDE.png@"
            ]
        },
      {
            "villager_count": 47,
            "age": 3,
            "resources": {
                "wood": 14,
                "food": 18,
                "gold": 5,
                "stone": 10
            },
            "notes": [
				"Build a 4th @town_center/Towncenter_aoe2DE.png@",
				"Up to 5 on @resource/Aoe2de_gold.png@",
				"Up to 10 on @resource/Aoe2de_stone.png@"
            ]
        },
		{
            "villager_count": 68,
            "age": 3,
            "resources": {
                "wood": 18,
                "food": 35,
                "gold": 5,
                "stone": 10
            },
            "notes": [
				"Research @mining_camp/GoldMiningDE.png@ + @mill/HeavyPlowDE.png@",
				"Up to 35 @resource/MaleVillDE.jpg@ on @mill/FarmDE.png@ and 18 on @resource/Aoe2de_wood.png@"
            ]
        },
		{
            "villager_count": 90,
            "age": 3,
            "resources": {
                "wood": 20,
                "food": 45,
                "gold": 5,
                "stone": 0
            },
            "notes": [
				"Build a @castle/Castle_aoe2DE.png@ with all the @resource/Aoe2de_stone.png@ @resource/MaleVillDE.jpg@",
				"Keep adding @mill/FarmDE.png@",
				"CLICK UP TO @age/ImperialAgeIconDE_alpha.png@"

            ]
        },
		{
            "villager_count": 90,
            "age": 3,
            "resources": {
                "wood": 20,
                "food": 25,
                "gold": 20,
                "stone": 0
            },
            "notes": [
				"@resource/Aoe2de_stone.png@ and new @resource/MaleVillDE.jpg@ to @resource/Aoe2de_gold.png@",
				"Research @blacksmith/ScaleBardingArmorDE.png@  @blacksmith/Forging_aoe2de.png@ ",
				"Build 6 @stable/Stable_aoe2DE.png@ research @stable/HusbandryDE.png@"
            ]
        },
		{
            "villager_count": 120,
            "age": 4,
            "resources": {
                "wood": 20,
                "food": 50,
                "gold": 40,
                "stone": 10
            },
            "notes": [
				"Up to 50 @resource/MaleVillDE.jpg@ on @mill/FarmDE.png@ and 40 on @resource/Aoe2de_gold.png@",
				"Produce @stable/Knight_aoe2DE.png@ on 6 @stable/Stable_aoe2DE.png@",
				"Research @blacksmith/ChainBardingDE.png@ @blacksmith/PlateBardingArmorDE.png@ @blacksmith/IronCastingDE.png@ @blacksmith/BlastFurnaceDE.png@@castle/ConscriptionDE.png@ @castle/Unique-tech-imperial.jpg@ @stable/Cavalier-research.jpg@ @stable/Paladin-research.jpg@",
				"10 @resource/MaleVillDE.jpg@ on @resource/Aoe2de_stone.png@ for future @castle/Castle_aoe2DE.png@"
            ]
        }
    ]
}
