{
    "name": "Ethiopians 20 pop archer",
    "author": "bigjoe_skiller",
    "source": "https://aoecompanion.com/b/ygecv5rfq9f",
    "build_order": [{
            "villager_count": 6,
            "age": 1,
            "resources": {
                "wood": 0,
                "food": {
					"Sheep": 6
				},
                "gold": 0,
                "stone": 0
            },
            "notes": [
                "Build 2 @other/House_aoe2DE.png@.",
                "Send the first 6 @resource/MaleVillDE.jpg@ to @animal/Sheep_aoe2DE.png@."
            ]
        },
        {
            "villager_count": 9,
            "age": 1,
            "resources": {
                "wood": 3,
                "food": {
					"Sheep": 6
				},
                "gold": 0,
                "stone": 0
            },
            "notes": [
                "Build the first @lumber_camp/Lumber_camp_aoe2de.png@.",
                "Send the next 3 @resource/MaleVillDE.jpg@ to @resource/Aoe2de_wood.png@."
            ]
        },
        {
            "villager_count": 10,
            "age": 1,
            "resources": {
                "wood": 3,
                "food": {
					"Boar": 7
				},
                "gold": 0,
                "stone": 0
            },
            "notes": [
                "Lure the first @animal/Boar_aoe2DE.png@. with the next @resource/MaleVillDE.jpg@"
            ]
        },
        {
            "villager_count": 13,
            "age": 1,
            "resources": {
                "wood": 3,
                "food": {
					"Boar": 7,
					"Sheep": 3
				},
                "gold": 0,
                "stone": 0
            },
            "notes": [
                "Add 3 @resource/MaleVillDE.jpg@ to @animal/Sheep_aoe2DE.png@ under @town_center/Towncenter_aoe2DE.png@.",
				"Build a @other/House_aoe2DE.png@ with @resource/Aoe2de_wood.png@ @resource/MaleVillDE.jpg@"
            ]
        },
        {
            "villager_count": 16,
            "age": 1,
            "resources": {
                "wood": 3,
                "food": {
					"Boar": 10,
					"Sheep": 3
				},
                "gold": 0,
                "stone": 0
            },
            "notes": [
                "Add 3 @resource/MaleVillDE.jpg@ to @animal/Boar_aoe2DE.png@",
				"Lure the second @animal/Boar_aoe2DE.png@"
            ]
        },
        {
            "villager_count": 17,
            "age": 1,
            "resources": {
                "wood": 3,
                "food": {
					"Boar": 10,
					"Sheep": 3
				},
                "gold": 1,
                "stone": 0
            },
            "notes": [
                "Send 1 @resource/MaleVillDE.jpg@ on a @resource/Aoe2de_gold.png@ @mining_camp/Mining_camp_aoe2de.png@"
            ]
        },
        {
            "villager_count": 19,
            "age": 1,
            "resources": {
                "wood": 3,
                "food": {
					"Sheep": 15
				},
                "gold": 1,
                "stone": 0
            },
            "notes": [
                "Add 2 @resource/MaleVillDE.jpg@ to @animal/Sheep_aoe2DE.png@"
            ]
        },
        {
            "villager_count": 19,
            "age": 1,
            "resources": {
                "wood": {
					"Lumber Camp": 9,
					"Stragglers": 5
				},
                "food": {
					"Sheep": 3
				},
                "gold": 1,
                "stone": 0
            },
            "notes": [
                "Research @town_center/LoomDE.png@, then click up to @age/FeudalAgeIconDE.png@",
				"6 from @animal/Sheep_aoe2DE.png@ to @resource/Aoe2de_wood.png@",
				"5 from @animal/Sheep_aoe2DE.png@ to stragglers",
				"1 from @animal/Sheep_aoe2DE.png@ to @other/House_aoe2DE.png@ and @barracks/Barracks_aoe2DE.png@"
            ]
        },
		{
            "villager_count": 19,
            "age": 1,
            "resources": {
                "wood": {
					"Lumber Camp": 12
				},
                "food": {
					"Berries": 4
				},
                "gold": 1,
                "stone": 0
            },
            "notes": [
				"When @animal/Sheep_aoe2DE.png@ run out, transfer to stragglers",
                "Just before @age/FeudalAgeIconDE.png@, 4 from stragglers to @resource/BerryBushDE.png@ and 1 builder"
				]
        },
		{
            "villager_count": 24,
            "age": 2,
            "resources": {
                "wood": {
					"Lumber Camp": 9
				},
                "food": {
					"Sheep": 3,
					"Berries": 4,
					"Farms": 3
				},
                "gold": 6,
                "stone": 0
            },
            "notes": [
                "Research @lumber_camp/DoubleBitAxe_aoe2DE.png@",
				"Place 2 @archery_range/Archery_range_aoe2DE.png@",
				"5 next @resource/MaleVillDE.jpg@ to @resource/Aoe2de_gold.png@",
				"Stragglers @resource/MaleVillDE.jpg@ to @mill/FarmDE.png@"
				]
        },
		{
            "villager_count": -1,
            "age": 2,
            "resources": {
                "wood": {
					"Lumber Camp": 9
				},
                "food": -1,
                "gold": 7,
                "stone": 0
            },
            "notes": [
                "1 Builder to @resource/Aoe2de_gold.png@",
				"1 Builder makes @other/House_aoe2DE.png@ + @blacksmith/Blacksmith_aoe2de.png@",
				"New @resource/MaleVillDE.jpg@ to @mill/FarmDE.png@",
				"Research @blacksmith/FletchingDE.png@"
				]
        }
    ]
}